smartutils/ID/__init__.py
smartutils/ID/abstract.py
smartutils/ID/const.py
smartutils/ID/gens/__init__.py
smartutils/ID/gens/snowflake.py
smartutils/ID/gens/ulid.py
smartutils/ID/gens/uuid.py
smartutils/ID/init.py
smartutils/__init__.py
smartutils/app/__init__.py
smartutils/app/adapter/__init__.py
smartutils/app/adapter/exception/__init__.py
smartutils/app/adapter/exception/aiohttp.py
smartutils/app/adapter/exception/django.py
smartutils/app/adapter/exception/fastapi.py
smartutils/app/adapter/exception/flask.py
smartutils/app/adapter/exception/sanic.py
smartutils/app/adapter/exception/tornado.py
smartutils/app/adapter/json_resp/__init__.py
smartutils/app/adapter/json_resp/_fastapi.py
smartutils/app/adapter/json_resp/aiohttp.py
smartutils/app/adapter/json_resp/django.py
smartutils/app/adapter/json_resp/factory.py
smartutils/app/adapter/json_resp/flask.py
smartutils/app/adapter/json_resp/sanic.py
smartutils/app/adapter/json_resp/tornado.py
smartutils/app/adapter/middleware/__init__.py
smartutils/app/adapter/middleware/abstract.py
smartutils/app/adapter/middleware/aiohttp.py
smartutils/app/adapter/middleware/django.py
smartutils/app/adapter/middleware/factory.py
smartutils/app/adapter/middleware/flask.py
smartutils/app/adapter/middleware/manager.py
smartutils/app/adapter/middleware/sanic.py
smartutils/app/adapter/middleware/starletee.py
smartutils/app/adapter/middleware/tornado.py
smartutils/app/adapter/req/__init__.py
smartutils/app/adapter/req/abstract.py
smartutils/app/adapter/req/aiohttp.py
smartutils/app/adapter/req/django.py
smartutils/app/adapter/req/factory.py
smartutils/app/adapter/req/flask.py
smartutils/app/adapter/req/sanic.py
smartutils/app/adapter/req/starlette.py
smartutils/app/adapter/req/tornado.py
smartutils/app/adapter/resp/__init__.py
smartutils/app/adapter/resp/abstract.py
smartutils/app/adapter/resp/aiohttp.py
smartutils/app/adapter/resp/django.py
smartutils/app/adapter/resp/factory.py
smartutils/app/adapter/resp/flask.py
smartutils_py-0.0.8.9.dist-info/METADATA
smartutils_py-0.0.8.9.dist-info/WHEEL
smartutils_py-0.0.8.9.dist-info/RECORD
