Metadata-Version: 2.4
Name: smartutils-py
Version: 0.0.8.9
Summary: 一个面向中大型项目的Python基础工具库，涵盖配置管理、日志、上下文、ID生成、数据处理、设计模式、定时、异常处理等基础功能。
License: MIT
Keywords: utils,python,基础工具,日志,配置,ID,设计模式,定时
Author: wuruimiao
Author-email: dev.wuruimiao@qq.com
Requires-Python: >=3.10,<4.0
Classifier: Development Status :: 4 - Beta
Classifier: Intended Audience :: Developers
Classifier: License :: OSI Approved :: MIT License
Classifier: Operating System :: OS Independent
Classifier: Programming Language :: Python
Classifier: Programming Language :: Python :: 3
Classifier: Programming Language :: Python :: 3.10
Classifier: Programming Language :: Python :: 3.11
Classifier: Programming Language :: Python :: 3.12
Classifier: Programming Language :: Python :: 3.13
Classifier: Programming Language :: Python :: 3.14
Classifier: Topic :: Software Development :: Libraries :: Python Modules
Provides-Extra: all
Provides-Extra: auth
Provides-Extra: client-grpc
Provides-Extra: client-http
Provides-Extra: django
Provides-Extra: fastapi
Provides-Extra: flask
Provides-Extra: kafka
Provides-Extra: mongo
Provides-Extra: mysql
Provides-Extra: opentelemetry
Provides-Extra: pgsql
Provides-Extra: redis
Requires-Dist: PyJWT (>=2.10.1,<2.11.0) ; extra == "auth" or extra == "all"
Requires-Dist: PyYAML (>=6.0.2,<6.1.0)
Requires-Dist: aiobreaker (>=1.2.0,<1.3.0) ; extra == "client-http" or extra == "client-grpc" or extra == "all"
Requires-Dist: aiokafka (>=0.12.0,<0.13.0) ; extra == "kafka" or extra == "all"
Requires-Dist: aioredlock (==0.7.3) ; extra == "redis"
Requires-Dist: asyncmy (>=0.2.10,<0.3.0) ; extra == "mysql" or extra == "all"
Requires-Dist: asyncpg (>=0.30.0,<0.31.0) ; extra == "pgsql" or extra == "all"
Requires-Dist: bcrypt (>=4.3.0,<4.4.0) ; extra == "auth" or extra == "all"
Requires-Dist: beanie (>=1.30.0,<2.0.0) ; extra == "mongo" or extra == "all"
Requires-Dist: contextvars (>=2.4,<2.5)
Requires-Dist: django (>=5.2.3,<5.3.0) ; extra == "django" or extra == "all"
Requires-Dist: fastapi (>=0.115.11,<0.116.0) ; extra == "fastapi" or extra == "all"
Requires-Dist: filetype (>=1.2.0,<2.0.0) ; extra == "all"
Requires-Dist: flask (>=3.1.1,<3.2.0) ; extra == "flask" or extra == "all"
Requires-Dist: grpcio (>=1.73.1,<1.74.0) ; extra == "client-grpc" or extra == "all"
Requires-Dist: httpx[socks] (>=0.28.1,<0.29.0) ; extra == "client-http" or extra == "all"
Requires-Dist: loguru (>=0.7.3,<0.8.0)
Requires-Dist: motor (>=3.7.1,<4.0.0) ; extra == "mongo" or extra == "all"
Requires-Dist: opentelemetry-exporter-otlp (>=1.35.0,<1.36.0) ; extra == "opentelemetry" or extra == "all"
Requires-Dist: opentelemetry-instrumentation-fastapi (>=0.56b0,<0.57) ; extra == "opentelemetry" or extra == "all"
Requires-Dist: opentelemetry-instrumentation-requests (>=0.56b0,<0.57) ; extra == "opentelemetry" or extra == "all"
Requires-Dist: opentelemetry-sdk (>=1.35.0,<1.36.0) ; extra == "opentelemetry" or extra == "all"
Requires-Dist: orjson (>=3.10.18,<3.11.0)
Requires-Dist: pillow (>=11.2.1,<11.3.0) ; extra == "auth" or extra == "all"
Requires-Dist: pydantic (>=2.10.6,<2.11.0)
Requires-Dist: pyotp (>=2.9.0,<2.10.0) ; extra == "auth" or extra == "all"
Requires-Dist: python-dotenv (>=1.1.0,<1.2.0)
Requires-Dist: python-snappy (>=0.7.3,<0.8.0) ; extra == "kafka" or extra == "all"
Requires-Dist: qrcode (>=8.1,<8.2) ; extra == "auth" or extra == "all"
Requires-Dist: redis (>=5.2.1,<5.3.0) ; extra == "redis" or extra == "all"
Requires-Dist: sqlalchemy[asyncio] (>=2.0.38,<2.1.0) ; extra == "mysql" or extra == "pgsql" or extra == "all"
Requires-Dist: starlette (>=0.46.2,<0.47.0) ; extra == "fastapi" or extra == "all"
Requires-Dist: uhashring (>=2.4,<2.5) ; extra == "all"
Requires-Dist: ulid-py (>=1.1.0,<1.2.0)
Requires-Dist: uvicorn[standard] (>=0.34.0,<0.35.0) ; extra == "fastapi" or extra == "all"
Requires-Dist: zstandard (>=0.23.0,<0.24.0) ; extra == "kafka" or extra == "all"
Project-URL: Homepage, https://github.com/wuruimiao/smartutils
Project-URL: Repository, https://github.com/wuruimiao/smartutils
